voter4.v
module voter_if (I, O);
input [3:0] I; // I 4 men
output [3:1] O; // O Result
reg [3:1] O;
    always@ (I)
        case (I)
            4'b0000:O[1] = 1;
            4'b0001:O[1] = 1;
            4'b0010:O[1] = 1;
            4'b0100:O[1] = 1;
            4'b1000:O[1] = 1;
            default:O[1] = 0;
        endcase
    always @(I) begin
        case (I)
            4'b0011:O[2] = 1;
            4'b0101:O[2] = 1;
            4'b0110:O[2] = 1;
            4'b1001:O[2] = 1;
            4'b1010:O[2] = 1;
            4'b1100:O[2] = 1;
            default:O[2] = 0;
        endcase
    end
    always @(I) begin
        case (I)
            4'b1110:O[3] = 1;
            4'b1101:O[3] = 1;
            4'b1011:O[3] = 1;
            4'b0111:O[3] = 1;
            4'b1111:O[3] = 1;
            default:O[3] = 0; 
        endcase
    end
endmodule

voter4_tb.v
module input_4_vote_tb;
reg [3:0] I;    //input
wire [3:1] O;   //output
initial begin
    //列舉出所有2的4次方的二進位
    #0 I = 4'b0000;
    #10 I = 4'b0001;
    #10 I = 4'b0010;
    #10 I = 4'b0011;
    #10 I = 4'b0100;
    #10 I = 4'b0101;
    #10 I = 4'b0110;
    #10 I = 4'b0111;
    #10 I = 4'b1000;
    #10 I = 4'b1001;
    #10 I = 4'b1010;
    #10 I = 4'b1011;
    #10 I = 4'b1100;
    #10 I = 4'b1101;
    #10 I = 4'b1110;
    #10 I = 4'b1111;
    #10 $finish;
end
voter_if vote4_tb(.I(I), .O(O));
initial begin
    $dumpfile("vote4.vcd");
    $dumpvars(0, vote4_tb);
end
endmodule

vote4.vcd
$date
	Mon Apr 25 03:30:49 2022
$end
$version
	Icarus Verilog
$end
$timescale
	1s
$end
$scope module input_4_vote_tb $end
$scope module vote4_tb $end
$var wire 4 ! I [3:0] $end
$var reg 3 " O [3:1] $end
$upscope $end
$upscope $end
$enddefinitions $end
#0
$dumpvars
b1 "
b0 !
$end
#10
b1 !
#20
b10 !
#30
b10 "
b11 !
#40
b1 "
b100 !
#50
b10 "
b101 !
#60
b110 !
#70
b100 "
b111 !
#80
b1 "
b1000 !
#90
b10 "
b1001 !
#100
b1010 !
#110
b100 "
b1011 !
#120
b10 "
b1100 !
#130
b100 "
b1101 !
#140
b1110 !
#150
b1111 !
